tests/__init__.py
tests/setup.py
tests/test_bq.py
tests/test_ftp.py
tests/test_mysql.py
tests/test_runner.py
tests/test_s3.py
tests/test_transfer.py
tmg/__init__.py
tmg/data/__init__.py
tmg/data/_helper.py
tmg/data/auth.py
tmg/data/bq.py
tmg/data/ftp.py
tmg/data/gs.py
tmg/data/logs.py
tmg/data/mysql.py
tmg/data/runner.py
tmg/data/s3.py
tmg/data/salesforce.py
tmg/data/sm.py
tmg/data/transfer.py
tmg_data-0.3.7.dist-info/licenses/LICENSE
tmg_data-0.3.7.dist-info/METADATA
tmg_data-0.3.7.dist-info/WHEEL
tmg_data-0.3.7.dist-info/top_level.txt
tmg_data-0.3.7.dist-info/RECORD
