Metadata-Version: 2.4
Name: tmg-data
Version: 0.3.7
Summary: TMG data library
Home-page: https://github.com/telegraph/tmg-data
Author: TMG Data Platform team
Author-email: data.platform@telegraph.co.uk
License: Apache 2.0
Classifier: Intended Audience :: Developers
Classifier: License :: OSI Approved :: Apache Software License
Classifier: Programming Language :: Python
Classifier: Programming Language :: Python :: 3
Classifier: Operating System :: OS Independent
Requires-Python: >=3.9
License-File: LICENSE
Requires-Dist: oauth2client==4.1.3
Requires-Dist: google-api-python-client==2.167.0
Requires-Dist: google-cloud-bigquery==3.31.0
Requires-Dist: google-cloud-storage==2.19.0
Requires-Dist: paramiko==3.5.1
Requires-Dist: Jinja2==3.1.6
Requires-Dist: mysql-connector==2.2.9
Requires-Dist: boto3==1.37.34
Requires-Dist: simple-salesforce==1.10.1
Requires-Dist: parse==1.15.0
Requires-Dist: delegator.py==0.1.1
Requires-Dist: markupsafe==3.0.2
Requires-Dist: pandas==2.2.3
Requires-Dist: pysftp==0.2.9
Dynamic: author
Dynamic: author-email
Dynamic: classifier
Dynamic: description
Dynamic: home-page
Dynamic: license
Dynamic: license-file
Dynamic: requires-dist
Dynamic: requires-python
Dynamic: summary
